hypermodern_python_test_this_is_a_test/__init__.py
hypermodern_python_test_this_is_a_test/console.py
hypermodern_python_test_this_is_a_test/wikipedia.py
hypermodern_python_test_this_is_a_test-1.0.0.dist-info/entry_points.txt
hypermodern_python_test_this_is_a_test-1.0.0.dist-info/LICENSE
hypermodern_python_test_this_is_a_test-1.0.0.dist-info/WHEEL
hypermodern_python_test_this_is_a_test-1.0.0.dist-info/METADATA
hypermodern_python_test_this_is_a_test-1.0.0.dist-info/RECORD
