Metadata-Version: 2.1
Name: hypermodern-python-test-this-is-a-test
Version: 1.0.0
Summary: Follow-along if hypermodern python project
Home-page: https://github.com/john-ingles/hypermodern_python_test
License: MIT
Keywords: hypermodern
Author: John Ingles
Author-email: john.kenneth.ingles@gmail.com
Requires-Python: >=3.9,<4.0
Classifier: License :: OSI Approved :: MIT License
Classifier: Programming Language :: Python :: 3
Classifier: Programming Language :: Python :: 3.10
Classifier: Programming Language :: Python :: 3.9
Requires-Dist: click (>=8.1.3,<9.0.0)
Requires-Dist: desert (>=2020.11.18,<2021.0.0)
Requires-Dist: importlib-metadata (>=4.12.0,<5.0.0); python_version < "3.9"
Requires-Dist: marshmallow (>=3.17.0,<4.0.0)
Requires-Dist: nox (>=2022.1.7,<2023.0.0)
Requires-Dist: requests (>=2.28.0,<3.0.0)
Project-URL: Repository, https://github.com/john-ingles/hypermodern_python_test
